setup_pyrailway.py
pynezha.egg-info/PKG-INFO
pynezha.egg-info/SOURCES.txt
pynezha.egg-info/dependency_links.txt
pynezha.egg-info/requires.txt
pynezha.egg-info/top_level.txt