Metadata-Version: 1.0
Name: pynezha
Version: 0.0.1
Summary: pyrailway, pysuway's railway
Home-page: https://github.com/kougazhang
Author: kougazhang
Author-email: kougazhang@gmail.com
License: UNKNOWN
Platform: UNKNOWN
